{"Response":{"Error":{"ErrorCode":0,"ErrorMessage":""},"FlightDetailChangeInfo":null,"IsPriceChanged":false,"ResponseStatus":1,"Results":{"IsHoldAllowedWithSSR":true,"ResultIndex":"OB26","Source":5,"IsLCC":false,"IsRefundable":true,"IsPanRequiredAtBook":false,"IsPanRequiredAtTicket":false,"IsPassportRequiredAtBook":false,"IsPassportRequiredAtTicket":false,"GSTAllowed":false,"IsCouponAppilcable":true,"IsGSTMandatory":false,"IsHoldAllowed":true,"AirlineRemark":"test uk remarks.","ResultFareType":"RegularFare","Fare":{"Currency":"INR","BaseFare":4670,"Tax":760,"TaxBreakup":[{"key":"K3","value":240},{"key":"YQTax","value":0},{"key":"YR","value":130},{"key":"PSF","value":0},{"key":"UDF","value":0},{"key":"INTax","value":63},{"key":"TransactionFee","value":0},{"key":"OtherTaxes","value":327}],"YQTax":0,"AdditionalTxnFeeOfrd":0,"AdditionalTxnFeePub":0,"PGCharge":0,"OtherCharges":0,"ChargeBU":[{"key":"TBOMARKUP","value":0},{"key":"GLOBALPROCUREMENTCHARGE","value":0},{"key":"CONVENIENCECHARGE","value":0},{"key":"OTHERCHARGE","value":0}],"Discount":0,"PublishedFare":5430,"CommissionEarned":0,"PLBEarned":0,"IncentiveEarned":0,"OfferedFare":5430,"TdsOnCommission":0,"TdsOnPLB":0,"TdsOnIncentive":0,"ServiceFee":0,"TotalBaggageCharges":0,"TotalMealCharges":0,"TotalSeatCharges":0,"TotalSpecialServiceCharges":0},"FareBreakdown":[{"Currency":"INR","PassengerType":1,"PassengerCount":1,"BaseFare":4670,"Tax":760,"TaxBreakUp":[{"key":"YR","value":130},{"key":"INTax","value":63},{"key":"K3","value":240},{"key":"OtherTaxes","value":327}],"YQTax":0,"AdditionalTxnFeeOfrd":0,"AdditionalTxnFeePub":0,"PGCharge":0,"SupplierReissueCharges":0}],"Segments":[[{"Baggage":"1Piece(s)","CabinBaggage":null,"CabinClass":2,"TripIndicator":1,"SegmentIndicator":1,"Airline":{"AirlineCode":"UK","AirlineName":"Vistara","FlightNumber":"945","FareClass":"O","OperatingCarrier":""},"Origin":{"Airport":{"AirportCode":"DEL","AirportName":"Indira Gandhi Airport","Terminal":"3","CityCode":"DEL","CityName":"Delhi","CountryCode":"IN","CountryName":"India"},"DepTime":"2022-11-24T11:40:00"},"Destination":{"Airport":{"AirportCode":"BOM","AirportName":"Mumbai","Terminal":"2","CityCode":"BOM","CityName":"Mumbai","CountryCode":"IN","CountryName":"India"},"ArrTime":"2022-11-24T13:55:00"},"Duration":135,"GroundTime":0,"Mile":0,"StopOver":false,"FlightInfoIndex":"","StopPoint":"","StopPointArrivalTime":"0001-01-01T00:00:00","StopPointDepartureTime":"0001-01-01T00:00:00","Craft":"320","Remark":null,"IsETicketEligible":true,"FlightStatus":"Confirmed","Status":"","FareClassification":{"Type":""}}]],"LastTicketDate":"2022-11-22T23:59:00.000","TicketAdvisory":null,"FareRules":[{"Origin":"DEL","Destination":"BOM","Airline":"UK","FareBasisCode":"O0NGLTYL","FareRuleDetail":"","FareRestriction":"","FareFamilyCode":"","FareRuleIndex":""}],"PenaltyCharges":{"ReissueCharge":"INR 3000","CancellationCharge":"INR 3500"},"AirlineCode":"UK","MiniFareRules":[[{"JourneyPoints":"DEL-BOM","Type":"Reissue","From":null,"To":null,"Unit":null,"Details":"INR 3000"},{"JourneyPoints":"DEL-BOM","Type":"Cancellation","From":null,"To":null,"Unit":null,"Details":"INR 3500"}]],"ValidatingAirline":"UK","FareClassification":{"Color":"Blue","Type":"Publish"}},"TraceId":"9a281a90-88ef-471b-a765-87f68e4406dd"}}